vectorlite_py/__init__.py
vectorlite_py/vectorlite.dll
vectorlite_py-0.2.0.dist-info/LICENSE
vectorlite_py-0.2.0.dist-info/METADATA
vectorlite_py-0.2.0.dist-info/WHEEL
vectorlite_py-0.2.0.dist-info/top_level.txt
vectorlite_py-0.2.0.dist-info/RECORD
